LICENSE
MANIFEST.in
requirements.txt
setup.cfg
setup.py
test_requirements.txt
eth_writer/__init__.py
eth_writer/interface.py
eth_writer.egg-info/PKG-INFO
eth_writer.egg-info/SOURCES.txt
eth_writer.egg-info/dependency_links.txt
eth_writer.egg-info/requires.txt
eth_writer.egg-info/top_level.txt
eth_writer/unittest/__init__.py
eth_writer/unittest/base.py