Metadata-Version: 2.1
Name: eth-writer
Version: 0.0.2
Summary: An interface for non-owner writer role to smart contract instance
Home-page: https://holbrook.no/src/eth-writer/log.html
Author: Louis Holbrook
Author-email: dev@holbrook.no
License: GPL3
Keywords: ethereum
Classifier: Programming Language :: Python :: 3
Classifier: Operating System :: OS Independent
Classifier: Development Status :: 3 - Alpha
Classifier: Environment :: No Input/Output (Daemon)
Classifier: Intended Audience :: Developers
Classifier: License :: OSI Approved :: GNU General Public License v3 or later (GPLv3+)
Classifier: Topic :: Internet
Classifier: Topic :: Software Development :: Libraries
Requires-Python: >=3.7
License-File: LICENSE
